LICENSE
ormar_casbin_adapter/__init__.py
ormar_casbin_adapter/adapter.py
ormar_casbin_adapter-0.0.2.dist-info/LICENSE
ormar_casbin_adapter-0.0.2.dist-info/WHEEL
ormar_casbin_adapter-0.0.2.dist-info/METADATA
ormar_casbin_adapter-0.0.2.dist-info/RECORD
