Metadata-Version: 2.1
Name: ormar-casbin-adapter
Version: 0.0.2
Summary: ormar casbin adapter
Home-page: https://github.com/shepilov-vladislav/ormar-casbin-adapter
License: Apache-2.0
Keywords: keyword,another_keyword
Author: Vladislav Shepilov
Author-email: shepilov.v@protonmail.com
Requires-Python: >=3.10,<4.0
Classifier: License :: OSI Approved :: Apache Software License
Classifier: Programming Language :: Python :: 3
Classifier: Programming Language :: Python :: 3.10
Requires-Dist: asynccasbin (>=1.1.8,<2.0.0)
Requires-Dist: ormar (>=0.11.0,<0.12.0)
Project-URL: Repository, https://github.com/shepilov-vladislav/ormar-casbin-adapter
